CafePy-0.0.1.data/scripts/cafepy.py
CafePy-0.0.1.dist-info/DESCRIPTION.rst
CafePy-0.0.1.dist-info/METADATA
CafePy-0.0.1.dist-info/RECORD
CafePy-0.0.1.dist-info/WHEEL
CafePy-0.0.1.dist-info/metadata.json
CafePy-0.0.1.dist-info/top_level.txt
cafepy/__init__.py
cafepy/__main__.py
cafepy/cafepy.py
cafepy/cafepy_base.py
cafepy/cafepy_error.py
cafepy/cafepy_memory_manager.py
cafepy/cafepy_stdout.py
cafepy/calc_cmap.py
cafepy/calc_com.py
cafepy/calc_distance.py
cafepy/calc_qscore.py
cafepy/file_io.py
cafepy/read_cafeinp.py
cafepy/read_dcd.py
cafepy/read_index.py
cafepy/read_movie.py
cafepy/read_ninfo.py
cafepy/read_pdb.py
cafepy/write_cafeinp.py
cafepy/write_dcd.py
cafepy/write_movie.py
cafepy/write_ninfo.py
src/__init__.py
src/cafepy.py
src/cafepy_base.py
src/cafepy_error.py
src/cafepy_memory_manager.py
src/cafepy_stdout.py
src/calc_cmap.py
src/calc_com.py
src/calc_distance.py
src/calc_qscore.py
src/file_io.py
src/read_cafeinp.py
src/read_dcd.py
src/read_index.py
src/read_movie.py
src/read_ninfo.py
src/read_pdb.py
src/write_cafeinp.py
src/write_dcd.py
src/write_movie.py
src/write_ninfo.py
