Metadata-Version: 2.0
Name: CafePy
Version: 0.0.1
Summary: Python Scripts For Analizing CafeMol Data.
Home-page: UNKNOWN
Author: Mogu
Author-email: kbu94984@gmail.com
License: UNKNOWN
Platform: UNKNOWN
